abhilasia/__init__.py
abhilasia/amrita.py
abhilasia/cli.py
abhilasia/core.py
abhilasia/distributed_shield.py
abhilasia-5.137.521.dist-info/METADATA
abhilasia-5.137.521.dist-info/WHEEL
abhilasia-5.137.521.dist-info/entry_points.txt
abhilasia-5.137.521.dist-info/top_level.txt
abhilasia-5.137.521.dist-info/RECORD
