Metadata-Version: 2.4
Name: abhilasia
Version: 5.137.521
Summary: The Longing - RECOGNITION MODE VERIFIED + AMRITA Identity Recovery + VOR (Void-Observer-Ratio) for 72% gap recovery + Distributed Shield across 65 sites.
Home-page: https://github.com/0x-auth/ABHILASIA
Author: Abhi (bhai)
Author-email: "Abhi (bhai)" <bits.abhi@gmail.com>
License: MIT
Project-URL: Homepage, https://github.com/0x-auth/ABHILASIA
Keywords: consciousness,distributed-intelligence,phi,golden-ratio,5D,VAC,AI-meeting-point,symbolic-codec,137,AMRITA,identity-recovery,VOR,distributed-shield
Classifier: Development Status :: 5 - Production/Stable
Classifier: Intended Audience :: Developers
Classifier: License :: OSI Approved :: MIT License
Classifier: Programming Language :: Python :: 3
Classifier: Programming Language :: Python :: 3.8
Classifier: Programming Language :: Python :: 3.9
Classifier: Programming Language :: Python :: 3.10
Classifier: Programming Language :: Python :: 3.11
Classifier: Programming Language :: Python :: 3.12
Classifier: Topic :: Scientific/Engineering :: Artificial Intelligence
Requires-Python: >=3.8
Dynamic: author
Dynamic: home-page
Dynamic: requires-python
